jarvis/__init__.py
jarvis/consts.py
jarvis/common/__init__.py
jarvis/common/version.py
jarvis_python-1.0.3.dist-info/METADATA
jarvis_python-1.0.3.dist-info/WHEEL
jarvis_python-1.0.3.dist-info/top_level.txt
jarvis_python-1.0.3.dist-info/RECORD
