Metadata-Version: 2.1
Name: jarvis-python
Version: 1.0.3
Summary: All in Jarvis!
Home-page: UNKNOWN
Author: killf
License: UNKNOWN
Keywords: workflow
Platform: UNKNOWN
Classifier: Operating System :: OS Independent
Classifier: Programming Language :: Python :: 3
Requires-Python: >=3.7
